<?xml version="1.0" encoding="utf-8"?>
<cnvrsText>
  <sheet name="en" index="1">
    <text name="fi5000_010" id="507273038" font="Range_FNT_subtitle" layout="Range_LAY_subtitle">
      You hooked <var name="fish_name" />!
    </text>
    <text name="fish000" id="1487008440" font="Range_FNT_subtitle" layout="Range_LAY_subtitle">
      a gourami
    </text>
    <text name="fish001" id="1487008441" font="Range_FNT_subtitle" layout="Range_LAY_subtitle">
      a loach
    </text>
    <text name="fish002" id="1487008442" font="Range_FNT_subtitle" layout="Range_LAY_subtitle">
      a medaka
    </text>
    <text name="fish003" id="1487008443" font="Range_FNT_subtitle" layout="Range_LAY_subtitle">
      a crayfish
    </text>
    <text name="fish004" id="1487008444" font="Range_FNT_subtitle" layout="Range_LAY_subtitle">
      a tadpole
    </text>
    <text name="fish005" id="1487008445" font="Range_FNT_subtitle" layout="Range_LAY_subtitle">
      a clownfish
    </text>
    <text name="fish006" id="1487008446" font="Range_FNT_subtitle" layout="Range_LAY_subtitle">
      a squid
    </text>
    <text name="fish007" id="1487008447" font="Range_FNT_subtitle" layout="Range_LAY_subtitle">
      a seahorse
    </text>
    <text name="fish008" id="1487008448" font="Range_FNT_subtitle" layout="Range_LAY_subtitle">
      a carp
    </text>
    <text name="fish009" id="1487008449" font="Range_FNT_subtitle" layout="Range_LAY_subtitle">
      a snapping turtle
    </text>
    <text name="fish010" id="1487008567" font="Range_FNT_subtitle" layout="Range_LAY_subtitle">
      a salmon
    </text>
    <text name="fish011" id="1487008568" font="Range_FNT_subtitle" layout="Range_LAY_subtitle">
      a flounder
    </text>
    <text name="fish012" id="1487008569" font="Range_FNT_subtitle" layout="Range_LAY_subtitle">
      an anglerfish
    </text>
    <text name="fish013" id="1487008570" font="Range_FNT_subtitle" layout="Range_LAY_subtitle">
      an octopus
    </text>
    <text name="fish014" id="1487008571" font="Range_FNT_subtitle" layout="Range_LAY_subtitle">
      a pufferfish
    </text>
    <text name="fish015" id="1487008572" font="Range_FNT_subtitle" layout="Range_LAY_subtitle">
      a crab
    </text>
    <text name="fish016" id="1487008573" font="Range_FNT_subtitle" layout="Range_LAY_subtitle">
      an alligator
    </text>
    <text name="fish017" id="1487008574" font="Range_FNT_subtitle" layout="Range_LAY_subtitle">
      a black bass
    </text>
    <text name="fish018" id="1487008575" font="Range_FNT_subtitle" layout="Range_LAY_subtitle">
      a nishiki koi
    </text>
    <text name="fish019" id="1487008576" font="Range_FNT_subtitle" layout="Range_LAY_subtitle">
      a coelacanth
    </text>
    <text name="fish020" id="1487008694" font="Range_FNT_subtitle" layout="Range_LAY_subtitle">
      an oarfish
    </text>
    <text name="fish021" id="1487008695" font="Range_FNT_subtitle" layout="Range_LAY_subtitle">
      a tuna
    </text>
    <text name="fish022" id="1487008696" font="Range_FNT_subtitle" layout="Range_LAY_subtitle">
      a sunfish
    </text>
    <text name="fish023" id="1487008697" font="Range_FNT_subtitle" layout="Range_LAY_subtitle">
      a marlin
    </text>
    <text name="fish024" id="1487008698" font="Range_FNT_subtitle" layout="Range_LAY_subtitle">
      a yellow spring
    </text>
    <text name="fish025" id="1487008699" font="Range_FNT_subtitle" layout="Range_LAY_subtitle">
      a red spring
    </text>
    <text name="fish026" id="1487008700" font="Range_FNT_subtitle" layout="Range_LAY_subtitle">
      a tin can
    </text>
    <text name="fish027" id="1487008701" font="Range_FNT_subtitle" layout="Range_LAY_subtitle">
      an Item Box
    </text>
    <text name="fish028" id="1487008702" font="Range_FNT_subtitle" layout="Range_LAY_subtitle">
      a Star Post
    </text>
    <text name="fish029" id="1487008703" font="Range_FNT_subtitle" layout="Range_LAY_subtitle">
      a Goal Plate
    </text>
    <text name="fish030" id="1487008821" font="Range_FNT_subtitle" layout="Range_LAY_subtitle">
      a Chopper
    </text>
    <text name="fish031" id="1487008822" font="Range_FNT_subtitle" layout="Range_LAY_subtitle">
      a twig
    </text>
    <text name="fish032" id="1487008823" font="Range_FNT_subtitle" layout="Range_LAY_subtitle">
      an acorn
    </text>
    <text name="fish033" id="1487008824" font="Range_FNT_subtitle" layout="Range_LAY_subtitle">
      a Ring
    </text>
    <text name="fish034" id="1487008825" font="Range_FNT_subtitle" layout="Range_LAY_subtitle">
      a tire
    </text>
    <text name="fish035" id="1487008826" font="Range_FNT_subtitle" layout="Range_LAY_subtitle">
      a barracuda
    </text>
    <text name="fish036" id="1487008827" font="Range_FNT_subtitle" layout="Range_LAY_subtitle">
      a stingray
    </text>
    <text name="fish037" id="1487008828" font="Range_FNT_subtitle" layout="Range_LAY_subtitle">
      a starfish
    </text>
    <text name="fish038" id="1487008829" font="Range_FNT_subtitle" layout="Range_LAY_subtitle">
      a poison dart frog
    </text>
    <text name="fish039" id="1487008830" font="Range_FNT_subtitle" layout="Range_LAY_subtitle">
      a goldfish
    </text>
    <text name="fish040" id="1487008948" font="Range_FNT_subtitle" layout="Range_LAY_subtitle">
      a flying fish
    </text>
    <text name="fish041" id="1487008949" font="Range_FNT_subtitle" layout="Range_LAY_subtitle">
      a giant isopod
    </text>
    <text name="fish042" id="1487008950" font="Range_FNT_subtitle" layout="Range_LAY_subtitle">
      a hammerhead shark
    </text>
    <text name="fish043" id="1487008951" font="Range_FNT_subtitle" layout="Range_LAY_subtitle">
      an ancient tablet
    </text>
    <text name="fish044" id="1487008952" font="Range_FNT_subtitle" layout="Range_LAY_subtitle">
      a moray eel
    </text>
    <text name="fish045" id="1487008953" font="Range_FNT_subtitle" layout="Range_LAY_subtitle">
      a polka-dot hammerhead shark
    </text>
    <text name="fish046" id="1487008954" font="Range_FNT_subtitle" layout="Range_LAY_subtitle">
      a red can
    </text>
    <text name="fish047" id="1487008955" font="Range_FNT_subtitle" layout="Range_LAY_subtitle">
      a silver acorn
    </text>
    <text name="fish048" id="1487008956" font="Range_FNT_subtitle" layout="Range_LAY_subtitle">
      a small Chopper
    </text>
    <text name="fish049" id="1487008957" font="Range_FNT_subtitle" layout="Range_LAY_subtitle">
      a platinum-golden fish
    </text>
    <text name="fish050" id="1487009075" font="Range_FNT_subtitle" layout="Range_LAY_subtitle">
      a blue-ringed octopus
    </text>
    <text name="fish051" id="1487009076" font="Range_FNT_subtitle" layout="Range_LAY_subtitle">
      a golden coelacanth
    </text>
    <text name="fish052" id="1487009077" font="Range_FNT_subtitle" layout="Range_LAY_subtitle">
      a king salmon
    </text>
    <text name="fish053" id="1487009078" font="Range_FNT_subtitle" layout="Range_LAY_subtitle">
      a black starfish
    </text>
    <text name="fish054" id="1487009079" font="Range_FNT_subtitle" layout="Range_LAY_subtitle">
      a flashy anglerfish
    </text>
    <text name="fish055" id="1487009080" font="Range_FNT_subtitle" layout="Range_LAY_subtitle">
      a red giant isopod
    </text>
    <text name="fish056" id="1487009081" font="Range_FNT_subtitle" layout="Range_LAY_subtitle">
      a red stingray
    </text>
    <text name="fish057" id="1487009082">
      a striped sunfish
    </text>
    <text name="fish058" id="1487009083">
      a big rainbow colored frog
    </text>
    <text name="fish085" id="1487009461">
      a Red Seed of Power
    </text>
    <text name="fish086" id="1487009462">
      a Blue Seed of Defense
    </text>
    <text name="fish090" id="1487009583">
      a Gold Card
    </text>
    <text name="fish091" id="1487009584">
      a Gold Card
    </text>
    <text name="fish092" id="1487009585">
      a Gold Card
    </text>
    <text name="fish093" id="1487009586">
      a Gold Card
    </text>
    <text name="fish094" id="1487009587">
      3 Gold Cards
    </text>
    <text name="fish095" id="1487009588">
      3 Gold Cards
    </text>
    <text name="fish096" id="1487009589">
      3 Gold Cards
    </text>
    <text name="fish097" id="1487009590">
      3 Gold Cards
    </text>
    <text name="fish098" id="1487009591">
      Elder Koco's scroll
    </text>
    <text name="fish099" id="1487009592">
      Elder Koco's scroll
    </text>
    <text name="fish100" id="1487024569" font="Range_FNT_subtitle" layout="Range_LAY_subtitle">
      Elder Koco's scroll
    </text>
    <text name="fish101" id="1487024570" font="Range_FNT_subtitle" layout="Range_LAY_subtitle">
      Elder Koco's scroll
    </text>
    <text name="fish102" id="1487024571" font="Range_FNT_subtitle" layout="Range_LAY_subtitle">
      Hermit Koco's scroll
    </text>
    <text name="fish103" id="1487024572" font="Range_FNT_subtitle" layout="Range_LAY_subtitle">
      Hermit Koco's scroll
    </text>
    <text name="fish104" id="1487024573" font="Range_FNT_subtitle" layout="Range_LAY_subtitle">
      Hermit Koco's scroll
    </text>
    <text name="fish105" id="1487024574" font="Range_FNT_subtitle" layout="Range_LAY_subtitle">
      Hermit Koco's scroll
    </text>
  </sheet>
  <fonts>
    <font name="Range_FNT_subtitle">
      <typeface>RANGEmixStd</typeface>
      <size>32</size>
      <lineSpacing>6</lineSpacing>
      <unknown1>1067450368</unknown1>
      <unknown2>2</unknown2>
      <unknown3>0</unknown3>
      <unknown4>0</unknown4>
    </font>
  </fonts>
  <layouts>
    <layout name="Range_LAY_subtitle">
      <textAlignment>centerLeft</textAlignment>
      <verticalAlignment>top</verticalAlignment>
      <wordWrap>true</wordWrap>
      <fit>none</fit>
    </layout>
  </layouts>
</cnvrsText>